dopy/__init__.py
dopy/cli.py
dopy/core.py
dopy/exceptions.py
dopy/help.py
dopy/transpiler/__init__.py
dopy/transpiler/collector.py
dopy/transpiler/processor.py
dopy_cli-0.2.0.dist-info/LICENSE
dopy_cli-0.2.0.dist-info/METADATA
dopy_cli-0.2.0.dist-info/WHEEL
dopy_cli-0.2.0.dist-info/entry_points.txt
dopy_cli-0.2.0.dist-info/RECORD
